[
  {
    "sensor_id": "TOS03005889",
    "timestamp": 1779402600,
    "value": -0.36,
    "unit": "m",
    "type": "hydrometric",
    "river": "Elsa",
    "province": "GR",
    "station_name": "SR74 Maremmana (RADIO)"
  },
  {
    "sensor_id": "TOS03005889",
    "timestamp": 1779408900,
    "value": -0.36,
    "unit": "m",
    "type": "hydrometric",
    "river": "Elsa",
    "province": "GR",
    "station_name": "SR74 Maremmana (RADIO)"
  },
  {
    "sensor_id": "TOS03005889",
    "timestamp": 1779424200,
    "value": -0.35,
    "unit": "m",
    "type": "hydrometric",
    "river": "Elsa",
    "province": "GR",
    "station_name": "SR74 Maremmana (RADIO)"
  },
  {
    "sensor_id": "TOS03005889",
    "timestamp": 1779435000,
    "value": -0.37,
    "unit": "m",
    "type": "hydrometric",
    "river": "Elsa",
    "province": "GR",
    "station_name": "SR74 Maremmana (RADIO)"
  },
  {
    "sensor_id": "TOS03005889",
    "timestamp": 1779445800,
    "value": -0.38,
    "unit": "m",
    "type": "hydrometric",
    "river": "Elsa",
    "province": "GR",
    "station_name": "SR74 Maremmana (RADIO)"
  }
]
