[
  {
    "sensor_id": "TOS03005487",
    "timestamp": 1778451300,
    "value": -0.76,
    "unit": "m",
    "type": "hydrometric",
    "river": "Cornia",
    "province": "LI",
    "station_name": "Cafaggio (RADIO)"
  },
  {
    "sensor_id": "TOS03005487",
    "timestamp": 1778457600,
    "value": -0.76,
    "unit": "m",
    "type": "hydrometric",
    "river": "Cornia",
    "province": "LI",
    "station_name": "Cafaggio (RADIO)"
  },
  {
    "sensor_id": "TOS03005487",
    "timestamp": 1778472000,
    "value": -0.76,
    "unit": "m",
    "type": "hydrometric",
    "river": "Cornia",
    "province": "LI",
    "station_name": "Cafaggio (RADIO)"
  },
  {
    "sensor_id": "TOS03005487",
    "timestamp": 1778483700,
    "value": -0.75,
    "unit": "m",
    "type": "hydrometric",
    "river": "Cornia",
    "province": "LI",
    "station_name": "Cafaggio (RADIO)"
  },
  {
    "sensor_id": "TOS03005487",
    "timestamp": 1778495400,
    "value": -0.75,
    "unit": "m",
    "type": "hydrometric",
    "river": "Cornia",
    "province": "LI",
    "station_name": "Cafaggio (RADIO)"
  },
  {
    "sensor_id": "TOS03005487",
    "timestamp": 1778505300,
    "value": -0.76,
    "unit": "m",
    "type": "hydrometric",
    "river": "Cornia",
    "province": "LI",
    "station_name": "Cafaggio (RADIO)"
  },
  {
    "sensor_id": "TOS03005487",
    "timestamp": 1778515200,
    "value": -0.76,
    "unit": "m",
    "type": "hydrometric",
    "river": "Cornia",
    "province": "LI",
    "station_name": "Cafaggio (RADIO)"
  },
  {
    "sensor_id": "TOS03005487",
    "timestamp": 1778522400,
    "value": -0.76,
    "unit": "m",
    "type": "hydrometric",
    "river": "Cornia",
    "province": "LI",
    "station_name": "Cafaggio (RADIO)"
  },
  {
    "sensor_id": "TOS03005487",
    "timestamp": 1778527800,
    "value": -0.76,
    "unit": "m",
    "type": "hydrometric",
    "river": "Cornia",
    "province": "LI",
    "station_name": "Cafaggio (RADIO)"
  }
]
