[
  {
    "sensor_id": "TOS03005141",
    "timestamp": 1781390700,
    "value": -0.04,
    "unit": "m",
    "type": "hydrometric",
    "river": "Era",
    "province": "PI",
    "station_name": "Ponte via Chiavaccini (RADIO)"
  },
  {
    "sensor_id": "TOS01005115",
    "timestamp": 1781391300,
    "value": 0.4,
    "unit": "m",
    "type": "hydrometric",
    "river": "Era",
    "province": "PI",
    "station_name": "Molino d'Era (GPRS)"
  },
  {
    "sensor_id": "TOS01005131",
    "timestamp": 1781391300,
    "value": 1.98,
    "unit": "m",
    "type": "hydrometric",
    "river": "Era",
    "province": "PI",
    "station_name": "Capannoli (GPRS)"
  },
  {
    "sensor_id": "TOS01005161",
    "timestamp": 1781391300,
    "value": 3.85,
    "unit": "m",
    "type": "hydrometric",
    "river": "Era",
    "province": "PI",
    "station_name": "Belvedere (GPRS)"
  },
  {
    "sensor_id": "TOS03005141",
    "timestamp": 1781408700,
    "value": -0.03,
    "unit": "m",
    "type": "hydrometric",
    "river": "Era",
    "province": "PI",
    "station_name": "Ponte via Chiavaccini (RADIO)"
  },
  {
    "sensor_id": "TOS01005115",
    "timestamp": 1781409600,
    "value": 0.43,
    "unit": "m",
    "type": "hydrometric",
    "river": "Era",
    "province": "PI",
    "station_name": "Molino d'Era (GPRS)"
  },
  {
    "sensor_id": "TOS01005131",
    "timestamp": 1781409600,
    "value": 1.98,
    "unit": "m",
    "type": "hydrometric",
    "river": "Era",
    "province": "PI",
    "station_name": "Capannoli (GPRS)"
  },
  {
    "sensor_id": "TOS01005161",
    "timestamp": 1781409600,
    "value": 3.85,
    "unit": "m",
    "type": "hydrometric",
    "river": "Era",
    "province": "PI",
    "station_name": "Belvedere (GPRS)"
  },
  {
    "sensor_id": "TOS03005141",
    "timestamp": 1781422200,
    "value": 0,
    "unit": "m",
    "type": "hydrometric",
    "river": "Era",
    "province": "PI",
    "station_name": "Ponte via Chiavaccini (RADIO)"
  },
  {
    "sensor_id": "TOS01005115",
    "timestamp": 1781422800,
    "value": 0.43,
    "unit": "m",
    "type": "hydrometric",
    "river": "Era",
    "province": "PI",
    "station_name": "Molino d'Era (GPRS)"
  },
  {
    "sensor_id": "TOS01005131",
    "timestamp": 1781422800,
    "value": 1.98,
    "unit": "m",
    "type": "hydrometric",
    "river": "Era",
    "province": "PI",
    "station_name": "Capannoli (GPRS)"
  },
  {
    "sensor_id": "TOS01005161",
    "timestamp": 1781422800,
    "value": 3.84,
    "unit": "m",
    "type": "hydrometric",
    "river": "Era",
    "province": "PI",
    "station_name": "Belvedere (GPRS)"
  },
  {
    "sensor_id": "TOS03005141",
    "timestamp": 1781432100,
    "value": -0.02,
    "unit": "m",
    "type": "hydrometric",
    "river": "Era",
    "province": "PI",
    "station_name": "Ponte via Chiavaccini (RADIO)"
  },
  {
    "sensor_id": "TOS01005115",
    "timestamp": 1781432400,
    "value": 0.4,
    "unit": "m",
    "type": "hydrometric",
    "river": "Era",
    "province": "PI",
    "station_name": "Molino d'Era (GPRS)"
  },
  {
    "sensor_id": "TOS01005131",
    "timestamp": 1781432400,
    "value": 1.98,
    "unit": "m",
    "type": "hydrometric",
    "river": "Era",
    "province": "PI",
    "station_name": "Capannoli (GPRS)"
  },
  {
    "sensor_id": "TOS01005161",
    "timestamp": 1781432400,
    "value": 3.84,
    "unit": "m",
    "type": "hydrometric",
    "river": "Era",
    "province": "PI",
    "station_name": "Belvedere (GPRS)"
  },
  {
    "sensor_id": "TOS03005141",
    "timestamp": 1781438400,
    "value": -0.01,
    "unit": "m",
    "type": "hydrometric",
    "river": "Era",
    "province": "PI",
    "station_name": "Ponte via Chiavaccini (RADIO)"
  },
  {
    "sensor_id": "TOS01005115",
    "timestamp": 1781438700,
    "value": 0.37,
    "unit": "m",
    "type": "hydrometric",
    "river": "Era",
    "province": "PI",
    "station_name": "Molino d'Era (GPRS)"
  },
  {
    "sensor_id": "TOS01005131",
    "timestamp": 1781438700,
    "value": 1.98,
    "unit": "m",
    "type": "hydrometric",
    "river": "Era",
    "province": "PI",
    "station_name": "Capannoli (GPRS)"
  },
  {
    "sensor_id": "TOS01005161",
    "timestamp": 1781438700,
    "value": 3.84,
    "unit": "m",
    "type": "hydrometric",
    "river": "Era",
    "province": "PI",
    "station_name": "Belvedere (GPRS)"
  }
]
