[
  {
    "sensor_id": "TOS03005831",
    "timestamp": 1779402600,
    "value": 0.69,
    "unit": "m",
    "type": "hydrometric",
    "river": "OmbroneGR",
    "province": "GR",
    "station_name": "Ponte Tura Aurelia (RADIO)"
  },
  {
    "sensor_id": "TOS03005831",
    "timestamp": 1779408900,
    "value": 0.69,
    "unit": "m",
    "type": "hydrometric",
    "river": "OmbroneGR",
    "province": "GR",
    "station_name": "Ponte Tura Aurelia (RADIO)"
  },
  {
    "sensor_id": "TOS03005831",
    "timestamp": 1779424200,
    "value": 0.67,
    "unit": "m",
    "type": "hydrometric",
    "river": "OmbroneGR",
    "province": "GR",
    "station_name": "Ponte Tura Aurelia (RADIO)"
  },
  {
    "sensor_id": "TOS03005831",
    "timestamp": 1779435000,
    "value": 0.66,
    "unit": "m",
    "type": "hydrometric",
    "river": "OmbroneGR",
    "province": "GR",
    "station_name": "Ponte Tura Aurelia (RADIO)"
  },
  {
    "sensor_id": "TOS03005831",
    "timestamp": 1779445800,
    "value": 0.66,
    "unit": "m",
    "type": "hydrometric",
    "river": "OmbroneGR",
    "province": "GR",
    "station_name": "Ponte Tura Aurelia (RADIO)"
  },
  {
    "sensor_id": "TOS03005831",
    "timestamp": 1779453900,
    "value": 0.65,
    "unit": "m",
    "type": "hydrometric",
    "river": "OmbroneGR",
    "province": "GR",
    "station_name": "Ponte Tura Aurelia (RADIO)"
  },
  {
    "sensor_id": "TOS03005831",
    "timestamp": 1779462900,
    "value": 0.65,
    "unit": "m",
    "type": "hydrometric",
    "river": "OmbroneGR",
    "province": "GR",
    "station_name": "Ponte Tura Aurelia (RADIO)"
  },
  {
    "sensor_id": "TOS03005831",
    "timestamp": 1779469200,
    "value": 0.65,
    "unit": "m",
    "type": "hydrometric",
    "river": "OmbroneGR",
    "province": "GR",
    "station_name": "Ponte Tura Aurelia (RADIO)"
  },
  {
    "sensor_id": "TOS03005831",
    "timestamp": 1779476400,
    "value": 0.65,
    "unit": "m",
    "type": "hydrometric",
    "river": "OmbroneGR",
    "province": "GR",
    "station_name": "Ponte Tura Aurelia (RADIO)"
  }
]
