[
  {
    "sensor_id": "TOS09001246",
    "timestamp": 1779660000,
    "value": 0.4,
    "unit": "m",
    "type": "hydrometric",
    "river": "Magra",
    "province": "MS",
    "station_name": "Calamazza ARPAL (RADIO)"
  },
  {
    "sensor_id": "TOS09001246",
    "timestamp": 1779668100,
    "value": 0.39,
    "unit": "m",
    "type": "hydrometric",
    "river": "Magra",
    "province": "MS",
    "station_name": "Calamazza ARPAL (RADIO)"
  },
  {
    "sensor_id": "TOS09001246",
    "timestamp": 1779684300,
    "value": 0.34,
    "unit": "m",
    "type": "hydrometric",
    "river": "Magra",
    "province": "MS",
    "station_name": "Calamazza ARPAL (RADIO)"
  },
  {
    "sensor_id": "TOS09001246",
    "timestamp": 1779701400,
    "value": 0.41,
    "unit": "m",
    "type": "hydrometric",
    "river": "Magra",
    "province": "MS",
    "station_name": "Calamazza ARPAL (RADIO)"
  }
]
