[
  {
    "sensor_id": "TOS01004784",
    "timestamp": 1778625300,
    "value": 0.17,
    "unit": "m",
    "type": "hydrometric",
    "river": "Marina",
    "province": "FI",
    "station_name": "Calenzano (GPRS)"
  },
  {
    "sensor_id": "TOS01004784",
    "timestamp": 1778631600,
    "value": 0.17,
    "unit": "m",
    "type": "hydrometric",
    "river": "Marina",
    "province": "FI",
    "station_name": "Calenzano (GPRS)"
  },
  {
    "sensor_id": "TOS01004784",
    "timestamp": 1778645100,
    "value": 0.16,
    "unit": "m",
    "type": "hydrometric",
    "river": "Marina",
    "province": "FI",
    "station_name": "Calenzano (GPRS)"
  },
  {
    "sensor_id": "TOS01004784",
    "timestamp": 1778655900,
    "value": 0.16,
    "unit": "m",
    "type": "hydrometric",
    "river": "Marina",
    "province": "FI",
    "station_name": "Calenzano (GPRS)"
  },
  {
    "sensor_id": "TOS01004784",
    "timestamp": 1778664900,
    "value": 0.15,
    "unit": "m",
    "type": "hydrometric",
    "river": "Marina",
    "province": "FI",
    "station_name": "Calenzano (GPRS)"
  },
  {
    "sensor_id": "TOS01004784",
    "timestamp": 1778671500,
    "value": 0.23,
    "unit": "m",
    "type": "hydrometric",
    "river": "Marina",
    "province": "FI",
    "station_name": "Calenzano (GPRS)"
  },
  {
    "sensor_id": "TOS01004784",
    "timestamp": 1778682600,
    "value": 0.22,
    "unit": "m",
    "type": "hydrometric",
    "river": "Marina",
    "province": "FI",
    "station_name": "Calenzano (GPRS)"
  },
  {
    "sensor_id": "TOS01004784",
    "timestamp": 1778690700,
    "value": 0.2,
    "unit": "m",
    "type": "hydrometric",
    "river": "Marina",
    "province": "FI",
    "station_name": "Calenzano (GPRS)"
  },
  {
    "sensor_id": "TOS01004784",
    "timestamp": 1778697600,
    "value": 0.2,
    "unit": "m",
    "type": "hydrometric",
    "river": "Marina",
    "province": "FI",
    "station_name": "Calenzano (GPRS)"
  },
  {
    "sensor_id": "TOS01004784",
    "timestamp": 1778703300,
    "value": 0.2,
    "unit": "m",
    "type": "hydrometric",
    "river": "Marina",
    "province": "FI",
    "station_name": "Calenzano (GPRS)"
  },
  {
    "sensor_id": "TOS01004784",
    "timestamp": 1778708100,
    "value": 0.19,
    "unit": "m",
    "type": "hydrometric",
    "river": "Marina",
    "province": "FI",
    "station_name": "Calenzano (GPRS)"
  }
]
