[
  {
    "sensor_id": "TOS15004865",
    "timestamp": 1784239200,
    "value": 0,
    "unit": "m",
    "type": "hydrometric",
    "river": "Ombrone PT",
    "province": "PO",
    "station_name": "Ponte alle Vanne Cassa (RADIO)"
  },
  {
    "sensor_id": "TOS15004865",
    "timestamp": 1784241900,
    "value": 0,
    "unit": "m",
    "type": "hydrometric",
    "river": "Ombrone PT",
    "province": "PO",
    "station_name": "Ponte alle Vanne Cassa (RADIO)"
  },
  {
    "sensor_id": "TOS15004865",
    "timestamp": 1784254500,
    "value": 0,
    "unit": "m",
    "type": "hydrometric",
    "river": "Ombrone PT",
    "province": "PO",
    "station_name": "Ponte alle Vanne Cassa (RADIO)"
  }
]
