[
  {
    "sensor_id": "TOS03006123",
    "timestamp": 1781736300,
    "value": 0.01,
    "unit": "m",
    "type": "hydrometric",
    "river": "Tevere",
    "province": "AR",
    "station_name": "Sansepolcro (RADIO)"
  },
  {
    "sensor_id": "TOS06006028",
    "timestamp": 1781737200,
    "value": 0.39,
    "unit": "m",
    "type": "hydrometric",
    "river": "Tevere",
    "province": "AR",
    "station_name": "Gorgabuia (RADIO)"
  },
  {
    "sensor_id": "TOS19000702",
    "timestamp": 1781737500,
    "value": -0.06,
    "unit": "m",
    "type": "hydrometric",
    "river": "Tevere",
    "province": "AR",
    "station_name": "Pieve S. Stefano (GPRS)"
  },
  {
    "sensor_id": "TOS06006028",
    "timestamp": 1781753400,
    "value": 0.39,
    "unit": "m",
    "type": "hydrometric",
    "river": "Tevere",
    "province": "AR",
    "station_name": "Gorgabuia (RADIO)"
  },
  {
    "sensor_id": "TOS03006123",
    "timestamp": 1781755200,
    "value": 0.01,
    "unit": "m",
    "type": "hydrometric",
    "river": "Tevere",
    "province": "AR",
    "station_name": "Sansepolcro (RADIO)"
  },
  {
    "sensor_id": "TOS19000702",
    "timestamp": 1781755500,
    "value": -0.06,
    "unit": "m",
    "type": "hydrometric",
    "river": "Tevere",
    "province": "AR",
    "station_name": "Pieve S. Stefano (GPRS)"
  },
  {
    "sensor_id": "TOS03006123",
    "timestamp": 1781771400,
    "value": 0,
    "unit": "m",
    "type": "hydrometric",
    "river": "Tevere",
    "province": "AR",
    "station_name": "Sansepolcro (RADIO)"
  },
  {
    "sensor_id": "TOS06006028",
    "timestamp": 1781771400,
    "value": 0.4,
    "unit": "m",
    "type": "hydrometric",
    "river": "Tevere",
    "province": "AR",
    "station_name": "Gorgabuia (RADIO)"
  },
  {
    "sensor_id": "TOS19000702",
    "timestamp": 1781772000,
    "value": -0.07,
    "unit": "m",
    "type": "hydrometric",
    "river": "Tevere",
    "province": "AR",
    "station_name": "Pieve S. Stefano (GPRS)"
  },
  {
    "sensor_id": "TOS03006123",
    "timestamp": 1781782200,
    "value": 0,
    "unit": "m",
    "type": "hydrometric",
    "river": "Tevere",
    "province": "AR",
    "station_name": "Sansepolcro (RADIO)"
  },
  {
    "sensor_id": "TOS06006028",
    "timestamp": 1781782200,
    "value": 0.39,
    "unit": "m",
    "type": "hydrometric",
    "river": "Tevere",
    "province": "AR",
    "station_name": "Gorgabuia (RADIO)"
  },
  {
    "sensor_id": "TOS19000702",
    "timestamp": 1781783100,
    "value": -0.08,
    "unit": "m",
    "type": "hydrometric",
    "river": "Tevere",
    "province": "AR",
    "station_name": "Pieve S. Stefano (GPRS)"
  },
  {
    "sensor_id": "TOS03006123",
    "timestamp": 1781794800,
    "value": 0,
    "unit": "m",
    "type": "hydrometric",
    "river": "Tevere",
    "province": "AR",
    "station_name": "Sansepolcro (RADIO)"
  },
  {
    "sensor_id": "TOS06006028",
    "timestamp": 1781794800,
    "value": 0.39,
    "unit": "m",
    "type": "hydrometric",
    "river": "Tevere",
    "province": "AR",
    "station_name": "Gorgabuia (RADIO)"
  },
  {
    "sensor_id": "TOS19000702",
    "timestamp": 1781795700,
    "value": -0.07,
    "unit": "m",
    "type": "hydrometric",
    "river": "Tevere",
    "province": "AR",
    "station_name": "Pieve S. Stefano (GPRS)"
  }
]
