[
  {
    "sensor_id": "TOS03003116",
    "timestamp": 1784239200,
    "value": 0.19,
    "unit": "m",
    "type": "hydrometric",
    "river": "Laguna",
    "province": "GR",
    "station_name": "Diga (GPRS)"
  },
  {
    "sensor_id": "TOS03003116",
    "timestamp": 1784242800,
    "value": 0.19,
    "unit": "m",
    "type": "hydrometric",
    "river": "Laguna",
    "province": "GR",
    "station_name": "Diga (GPRS)"
  },
  {
    "sensor_id": "TOS03003116",
    "timestamp": 1784255400,
    "value": 0.19,
    "unit": "m",
    "type": "hydrometric",
    "river": "Laguna",
    "province": "GR",
    "station_name": "Diga (GPRS)"
  },
  {
    "sensor_id": "TOS03003116",
    "timestamp": 1784264400,
    "value": 0.18,
    "unit": "m",
    "type": "hydrometric",
    "river": "Laguna",
    "province": "GR",
    "station_name": "Diga (GPRS)"
  },
  {
    "sensor_id": "TOS03003116",
    "timestamp": 1784272500,
    "value": 0.19,
    "unit": "m",
    "type": "hydrometric",
    "river": "Laguna",
    "province": "GR",
    "station_name": "Diga (GPRS)"
  },
  {
    "sensor_id": "TOS03003116",
    "timestamp": 1784278800,
    "value": 0.18,
    "unit": "m",
    "type": "hydrometric",
    "river": "Laguna",
    "province": "GR",
    "station_name": "Diga (GPRS)"
  },
  {
    "sensor_id": "TOS03003116",
    "timestamp": 1784285100,
    "value": 0.18,
    "unit": "m",
    "type": "hydrometric",
    "river": "Laguna",
    "province": "GR",
    "station_name": "Diga (GPRS)"
  },
  {
    "sensor_id": "TOS03003116",
    "timestamp": 1784289600,
    "value": 0.18,
    "unit": "m",
    "type": "hydrometric",
    "river": "Laguna",
    "province": "GR",
    "station_name": "Diga (GPRS)"
  },
  {
    "sensor_id": "TOS03003116",
    "timestamp": 1784295900,
    "value": 0.18,
    "unit": "m",
    "type": "hydrometric",
    "river": "Laguna",
    "province": "GR",
    "station_name": "Diga (GPRS)"
  },
  {
    "sensor_id": "TOS03003116",
    "timestamp": 1784300400,
    "value": 0.18,
    "unit": "m",
    "type": "hydrometric",
    "river": "Laguna",
    "province": "GR",
    "station_name": "Diga (GPRS)"
  },
  {
    "sensor_id": "TOS03003116",
    "timestamp": 1784304900,
    "value": 0.18,
    "unit": "m",
    "type": "hydrometric",
    "river": "Laguna",
    "province": "GR",
    "station_name": "Diga (GPRS)"
  }
]
