[
  {
    "sensor_id": "TOS01004641",
    "timestamp": 1779748200,
    "value": 0.51,
    "unit": "m",
    "type": "hydrometric",
    "river": "Sieve",
    "province": "FI",
    "station_name": "Fornacina (GPRS)"
  },
  {
    "sensor_id": "TOS01004641",
    "timestamp": 1779754800,
    "value": 0.5,
    "unit": "m",
    "type": "hydrometric",
    "river": "Sieve",
    "province": "FI",
    "station_name": "Fornacina (GPRS)"
  },
  {
    "sensor_id": "TOS01004641",
    "timestamp": 1779770100,
    "value": 0.51,
    "unit": "m",
    "type": "hydrometric",
    "river": "Sieve",
    "province": "FI",
    "station_name": "Fornacina (GPRS)"
  }
]
