[
  {
    "sensor_id": "TOS01005005",
    "timestamp": 1778079300,
    "value": 0.15,
    "unit": "m",
    "type": "hydrometric",
    "river": "Egola",
    "province": "PI",
    "station_name": "Fornacino (GPRS)"
  },
  {
    "sensor_id": "TOS01005005",
    "timestamp": 1778082300,
    "value": 0.12,
    "unit": "m",
    "type": "hydrometric",
    "river": "Egola",
    "province": "PI",
    "station_name": "Fornacino (GPRS)"
  },
  {
    "sensor_id": "TOS01005005",
    "timestamp": 1778082600,
    "value": 0.12,
    "unit": "m",
    "type": "hydrometric",
    "river": "Egola",
    "province": "PI",
    "station_name": "Fornacino (GPRS)"
  },
  {
    "sensor_id": "TOS01005005",
    "timestamp": 1778084700,
    "value": 0.12,
    "unit": "m",
    "type": "hydrometric",
    "river": "Egola",
    "province": "PI",
    "station_name": "Fornacino (GPRS)"
  },
  {
    "sensor_id": "TOS01005005",
    "timestamp": 1778086800,
    "value": 0.12,
    "unit": "m",
    "type": "hydrometric",
    "river": "Egola",
    "province": "PI",
    "station_name": "Fornacino (GPRS)"
  },
  {
    "sensor_id": "TOS01005005",
    "timestamp": 1778093700,
    "value": 1.18,
    "unit": "m",
    "type": "hydrometric",
    "river": "Egola",
    "province": "PI",
    "station_name": "Fornacino (GPRS)"
  },
  {
    "sensor_id": "TOS01005005",
    "timestamp": 1778098500,
    "value": 0.81,
    "unit": "m",
    "type": "hydrometric",
    "river": "Egola",
    "province": "PI",
    "station_name": "Fornacino (GPRS)"
  },
  {
    "sensor_id": "TOS01005005",
    "timestamp": 1778101500,
    "value": 1.01,
    "unit": "m",
    "type": "hydrometric",
    "river": "Egola",
    "province": "PI",
    "station_name": "Fornacino (GPRS)"
  }
]
