[
  {
    "sensor_id": "TOS03005615",
    "timestamp": 1780528500,
    "value": 0.89,
    "unit": "m",
    "type": "hydrometric",
    "river": "Sovata",
    "province": "GR",
    "station_name": "Sovata (RADIO)"
  },
  {
    "sensor_id": "TOS03005615",
    "timestamp": 1780545600,
    "value": 0.89,
    "unit": "m",
    "type": "hydrometric",
    "river": "Sovata",
    "province": "GR",
    "station_name": "Sovata (RADIO)"
  },
  {
    "sensor_id": "TOS03005615",
    "timestamp": 1780560000,
    "value": 0.87,
    "unit": "m",
    "type": "hydrometric",
    "river": "Sovata",
    "province": "GR",
    "station_name": "Sovata (RADIO)"
  },
  {
    "sensor_id": "TOS03005615",
    "timestamp": 1780571400,
    "value": 0.87,
    "unit": "m",
    "type": "hydrometric",
    "river": "Sovata",
    "province": "GR",
    "station_name": "Sovata (GPRS)"
  },
  {
    "sensor_id": "TOS03005615",
    "timestamp": 1780584600,
    "value": 0.89,
    "unit": "m",
    "type": "hydrometric",
    "river": "Sovata",
    "province": "GR",
    "station_name": "Sovata (GPRS)"
  },
  {
    "sensor_id": "TOS03005615",
    "timestamp": 1780592700,
    "value": 0.9,
    "unit": "m",
    "type": "hydrometric",
    "river": "Sovata",
    "province": "GR",
    "station_name": "Sovata (GPRS)"
  }
]
