[
  {
    "sensor_id": "TOS16005841",
    "timestamp": 1780351200,
    "value": 1.33,
    "unit": "m",
    "type": "hydrometric",
    "river": "OmbroneGR",
    "province": "GR",
    "station_name": "Berrettino (RADIO)"
  },
  {
    "sensor_id": "TOS16005841",
    "timestamp": 1780360200,
    "value": 1.34,
    "unit": "m",
    "type": "hydrometric",
    "river": "OmbroneGR",
    "province": "GR",
    "station_name": "Berrettino (RADIO)"
  },
  {
    "sensor_id": "TOS16005841",
    "timestamp": 1780376400,
    "value": 1.33,
    "unit": "m",
    "type": "hydrometric",
    "river": "OmbroneGR",
    "province": "GR",
    "station_name": "Berrettino (RADIO)"
  },
  {
    "sensor_id": "TOS16005841",
    "timestamp": 1780393500,
    "value": 1.33,
    "unit": "m",
    "type": "hydrometric",
    "river": "OmbroneGR",
    "province": "GR",
    "station_name": "Berrettino (RADIO)"
  },
  {
    "sensor_id": "TOS16005841",
    "timestamp": 1780408800,
    "value": 1.33,
    "unit": "m",
    "type": "hydrometric",
    "river": "OmbroneGR",
    "province": "GR",
    "station_name": "Berrettino (RADIO)"
  }
]
