[
  {
    "sensor_id": "TOS30250000",
    "timestamp": 1778197500,
    "value": 0.36,
    "unit": "m",
    "type": "hydrometric",
    "river": "Lamone",
    "province": "FI",
    "station_name": "Marradi (RADIO)"
  },
  {
    "sensor_id": "TOS30250000",
    "timestamp": 1778208300,
    "value": 0.35,
    "unit": "m",
    "type": "hydrometric",
    "river": "Lamone",
    "province": "FI",
    "station_name": "Marradi (RADIO)"
  },
  {
    "sensor_id": "TOS30250000",
    "timestamp": 1778215500,
    "value": 0.34,
    "unit": "m",
    "type": "hydrometric",
    "river": "Lamone",
    "province": "FI",
    "station_name": "Marradi (RADIO)"
  },
  {
    "sensor_id": "TOS30250000",
    "timestamp": 1778220900,
    "value": 0.33,
    "unit": "m",
    "type": "hydrometric",
    "river": "Lamone",
    "province": "FI",
    "station_name": "Marradi (RADIO)"
  },
  {
    "sensor_id": "TOS30250000",
    "timestamp": 1778228100,
    "value": 0.32,
    "unit": "m",
    "type": "hydrometric",
    "river": "Lamone",
    "province": "FI",
    "station_name": "Marradi (RADIO)"
  }
]
