[
  {
    "sensor_id": "TOS03005141",
    "timestamp": 1778107500,
    "value": 0.33,
    "unit": "m",
    "type": "hydrometric",
    "river": "Era",
    "province": "PI",
    "station_name": "Ponte via Chiavaccini (RADIO)"
  },
  {
    "sensor_id": "TOS03005141",
    "timestamp": 1778121900,
    "value": 0.28,
    "unit": "m",
    "type": "hydrometric",
    "river": "Era",
    "province": "PI",
    "station_name": "Ponte via Chiavaccini (RADIO)"
  },
  {
    "sensor_id": "TOS03005141",
    "timestamp": 1778131800,
    "value": 0.28,
    "unit": "m",
    "type": "hydrometric",
    "river": "Era",
    "province": "PI",
    "station_name": "Ponte via Chiavaccini (RADIO)"
  }
]
