[
  {
    "sensor_id": "TOS19000704",
    "timestamp": 1781215200,
    "value": 0.27,
    "unit": "m",
    "type": "hydrometric",
    "river": "Ema",
    "province": "FI",
    "station_name": "Grassina (RADIO)"
  },
  {
    "sensor_id": "TOS19000704",
    "timestamp": 1781224200,
    "value": 0.27,
    "unit": "m",
    "type": "hydrometric",
    "river": "Ema",
    "province": "FI",
    "station_name": "Grassina (RADIO)"
  },
  {
    "sensor_id": "TOS19000704",
    "timestamp": 1781240400,
    "value": 0.28,
    "unit": "m",
    "type": "hydrometric",
    "river": "Ema",
    "province": "FI",
    "station_name": "Grassina (RADIO)"
  },
  {
    "sensor_id": "TOS19000704",
    "timestamp": 1781256600,
    "value": 0.28,
    "unit": "m",
    "type": "hydrometric",
    "river": "Ema",
    "province": "FI",
    "station_name": "Grassina (RADIO)"
  },
  {
    "sensor_id": "TOS19000704",
    "timestamp": 1781268300,
    "value": 0.28,
    "unit": "m",
    "type": "hydrometric",
    "river": "Ema",
    "province": "FI",
    "station_name": "Grassina (RADIO)"
  },
  {
    "sensor_id": "TOS19000704",
    "timestamp": 1781278200,
    "value": 0.28,
    "unit": "m",
    "type": "hydrometric",
    "river": "Ema",
    "province": "FI",
    "station_name": "Grassina (RADIO)"
  },
  {
    "sensor_id": "TOS19000704",
    "timestamp": 1781286300,
    "value": 0.28,
    "unit": "m",
    "type": "hydrometric",
    "river": "Ema",
    "province": "FI",
    "station_name": "Grassina (RADIO)"
  }
]
