[
  {
    "sensor_id": "TOS15004682",
    "timestamp": 1784844900,
    "value": 2.23,
    "unit": "m",
    "type": "hydrometric",
    "river": "Arno",
    "province": "FI",
    "station_name": "Firenze Uffizi 2 (RADIO)"
  },
  {
    "sensor_id": "TOS15004682",
    "timestamp": 1784850300,
    "value": 2.23,
    "unit": "m",
    "type": "hydrometric",
    "river": "Arno",
    "province": "FI",
    "station_name": "Firenze Uffizi 2 (RADIO)"
  },
  {
    "sensor_id": "TOS15004682",
    "timestamp": 1784862900,
    "value": 2.23,
    "unit": "m",
    "type": "hydrometric",
    "river": "Arno",
    "province": "FI",
    "station_name": "Firenze Uffizi 2 (RADIO)"
  },
  {
    "sensor_id": "TOS15004682",
    "timestamp": 1784872800,
    "value": 2.22,
    "unit": "m",
    "type": "hydrometric",
    "river": "Arno",
    "province": "FI",
    "station_name": "Firenze Uffizi 2 (RADIO)"
  },
  {
    "sensor_id": "TOS15004682",
    "timestamp": 1784880900,
    "value": 2.23,
    "unit": "m",
    "type": "hydrometric",
    "river": "Arno",
    "province": "FI",
    "station_name": "Firenze Uffizi 2 (RADIO)"
  },
  {
    "sensor_id": "TOS15004682",
    "timestamp": 1784887200,
    "value": 2.23,
    "unit": "m",
    "type": "hydrometric",
    "river": "Arno",
    "province": "FI",
    "station_name": "Firenze Uffizi 2 (RADIO)"
  },
  {
    "sensor_id": "TOS15004682",
    "timestamp": 1784893500,
    "value": 2.23,
    "unit": "m",
    "type": "hydrometric",
    "river": "Arno",
    "province": "FI",
    "station_name": "Firenze Uffizi 2 (RADIO)"
  },
  {
    "sensor_id": "TOS15004682",
    "timestamp": 1784899800,
    "value": 2.23,
    "unit": "m",
    "type": "hydrometric",
    "river": "Arno",
    "province": "FI",
    "station_name": "Firenze Uffizi 2 (RADIO)"
  },
  {
    "sensor_id": "TOS15004682",
    "timestamp": 1784906100,
    "value": 2.23,
    "unit": "m",
    "type": "hydrometric",
    "river": "Arno",
    "province": "FI",
    "station_name": "Firenze Uffizi 2 (RADIO)"
  },
  {
    "sensor_id": "TOS15004682",
    "timestamp": 1784911500,
    "value": 2.23,
    "unit": "m",
    "type": "hydrometric",
    "river": "Arno",
    "province": "FI",
    "station_name": "Firenze Uffizi 2 (RADIO)"
  },
  {
    "sensor_id": "TOS15004682",
    "timestamp": 1784916900,
    "value": 2.23,
    "unit": "m",
    "type": "hydrometric",
    "river": "Arno",
    "province": "FI",
    "station_name": "Firenze Uffizi 2 (RADIO)"
  },
  {
    "sensor_id": "TOS15004682",
    "timestamp": 1784921400,
    "value": 2.23,
    "unit": "m",
    "type": "hydrometric",
    "river": "Arno",
    "province": "FI",
    "station_name": "Firenze Uffizi 2 (RADIO)"
  },
  {
    "sensor_id": "TOS15004682",
    "timestamp": 1784925000,
    "value": 2.23,
    "unit": "m",
    "type": "hydrometric",
    "river": "Arno",
    "province": "FI",
    "station_name": "Firenze Uffizi 2 (RADIO)"
  }
]
