[
  {
    "sensor_id": "TOS02004101",
    "timestamp": 1784844900,
    "value": 0.24,
    "unit": "m",
    "type": "hydrometric",
    "river": "Canale Burlamacca",
    "province": "LU",
    "station_name": "Viareggio 2 (RADIO)"
  },
  {
    "sensor_id": "TOS02004091",
    "timestamp": 1784845800,
    "value": -0.19,
    "unit": "m",
    "type": "hydrometric",
    "river": "Canale Burlamacca",
    "province": "LU",
    "station_name": "Viareggio 1 (GPRS)"
  },
  {
    "sensor_id": "TOS02004101",
    "timestamp": 1784850300,
    "value": 0.26,
    "unit": "m",
    "type": "hydrometric",
    "river": "Canale Burlamacca",
    "province": "LU",
    "station_name": "Viareggio 2 (RADIO)"
  },
  {
    "sensor_id": "TOS02004091",
    "timestamp": 1784851200,
    "value": -0.19,
    "unit": "m",
    "type": "hydrometric",
    "river": "Canale Burlamacca",
    "province": "LU",
    "station_name": "Viareggio 1 (GPRS)"
  },
  {
    "sensor_id": "TOS02004101",
    "timestamp": 1784862900,
    "value": 0.24,
    "unit": "m",
    "type": "hydrometric",
    "river": "Canale Burlamacca",
    "province": "LU",
    "station_name": "Viareggio 2 (RADIO)"
  },
  {
    "sensor_id": "TOS02004091",
    "timestamp": 1784863500,
    "value": -0.19,
    "unit": "m",
    "type": "hydrometric",
    "river": "Canale Burlamacca",
    "province": "LU",
    "station_name": "Viareggio 1 (GPRS)"
  }
]
